sfpl/__init__.py
sfpl/exceptions.py
sfpl/sfpl.py
sfpl-1.5.7.dist-info/licenses/LICENSE.md
sfpl-1.5.7.dist-info/METADATA
sfpl-1.5.7.dist-info/WHEEL
sfpl-1.5.7.dist-info/top_level.txt
sfpl-1.5.7.dist-info/RECORD
