Metadata-Version: 2.4
Name: sfpl
Version: 1.5.7
Summary: Unofficial Python API for SFPL
Home-page: https://github.com/kajchang/sfpl-scraper
Author: Kai Chang
Author-email: kaijchang@gmail.com
License: MIT
License-File: LICENSE.md
Requires-Dist: beautifulsoup4~=4.13.4
Requires-Dist: requests~=2.31.0
Requires-Dist: lxml~=5.4.0
Dynamic: author
Dynamic: author-email
Dynamic: description
Dynamic: description-content-type
Dynamic: home-page
Dynamic: license
Dynamic: license-file
Dynamic: requires-dist
Dynamic: summary
